{"nodes": [{"id": "c_myproject_narriv_frontend_components_dashboard_platformbarchart_tsx", "label": "PlatformBarChart.tsx", "file_type": "code", "source_file": "C:\\MyProject\\narriv\\frontend\\components\\dashboard\\PlatformBarChart.tsx", "source_location": "L1"}], "edges": [{"source": "c_myproject_narriv_frontend_components_dashboard_platformbarchart_tsx", "target": "react", "relation": "imports_from", "confidence": "EXTRACTED", "source_file": "C:\\MyProject\\narriv\\frontend\\components\\dashboard\\PlatformBarChart.tsx", "source_location": "L3", "weight": 1.0}, {"source": "c_myproject_narriv_frontend_components_dashboard_platformbarchart_tsx", "target": "recharts", "relation": "imports_from", "confidence": "EXTRACTED", "source_file": "C:\\MyProject\\narriv\\frontend\\components\\dashboard\\PlatformBarChart.tsx", "source_location": "L4", "weight": 1.0}], "raw_calls": []}